extractimail/__init__.py
extractimail/__main__.py
extractimail/config.py
extractimail/main.py
extractimail/setup_ui.py
extractimail-1.1.0.dist-info/METADATA
extractimail-1.1.0.dist-info/WHEEL
extractimail-1.1.0.dist-info/entry_points.txt
extractimail-1.1.0.dist-info/top_level.txt
extractimail-1.1.0.dist-info/RECORD
