Metadata-Version: 2.1
Name: extractimail
Version: 1.1.0
Summary: A tool to automatically recollect emails and save attachments.
Author: Federico Toscano
Author-email: federico.toscano@axpo.com
Classifier: Programming Language :: Python :: 3
Classifier: Operating System :: Microsoft :: Windows
Requires-Python: >=3.6
Requires-Dist: pywin32
Requires-Dist: PyPDF2
Requires-Dist: pandas
